aicp/__init__.py
aicp/lib.py
aicp/main.py
aicp/service.py
aicp/solution.py
aicp-0.1.3.dist-info/entry_points.txt
aicp-0.1.3.dist-info/WHEEL
aicp-0.1.3.dist-info/METADATA
aicp-0.1.3.dist-info/RECORD
